email_broadcasting/__init__.py
email_broadcasting/core/__init__.py
email_broadcasting/core/_async.py
email_broadcasting/core/_base.py
email_broadcasting/core/_sync.py
email_broadcasting-0.1.4.dist-info/LICENSE
email_broadcasting-0.1.4.dist-info/METADATA
email_broadcasting-0.1.4.dist-info/WHEEL
email_broadcasting-0.1.4.dist-info/RECORD
