Metadata-Version: 2.1
Name: email-broadcasting
Version: 0.1.4
Summary: Implement simple email broadcasting interface.
Home-page: https://github.com/Deskent/email_broadcasting
License: MIT
Author: deskent
Author-email: battenetciz@gmail.com
Requires-Python: >=3.11,<4.0
Classifier: License :: OSI Approved :: MIT License
Classifier: Programming Language :: Python :: 3
Classifier: Programming Language :: Python :: 3.11
Classifier: Programming Language :: Python :: 3.12
Project-URL: Repository, https://github.com/Deskent/email_broadcasting
